.gitignore
LICENSE
README.md
pyproject.toml
.github/workflows/python-publish.yml
docs/Makefile
docs/abbrev_long.bib
docs/conf.py
docs/conf_overrides.py
docs/conf_spec.py
docs/index.rst
docs/make.bat
docs/references.bib
docs/_static/styles/my_theme.css
docs/_templates/autoapi/index.rst
docs/_templates/autoapi/python/attribute.rst
docs/_templates/autoapi/python/class.rst
docs/_templates/autoapi/python/data.rst
docs/_templates/autoapi/python/exception.rst
docs/_templates/autoapi/python/function.rst
docs/_templates/autoapi/python/method.rst
docs/_templates/autoapi/python/module.rst
docs/_templates/autoapi/python/package.rst
docs/_templates/autoapi/python/property.rst
src/cameravision/__init__.py
src/cameravision/_version.py
src/cameravision/cameravision.py
src/cameravision/coordframes.py
src/cameravision/decorators.py
src/cameravision/distortion.py
src/cameravision/maps.py
src/cameravision/maps_impl.py
src/cameravision/points_impl.py
src/cameravision/precompile.py
src/cameravision/reprojection.py
src/cameravision/util.py
src/cameravision/validity.py
src/cameravision.egg-info/PKG-INFO
src/cameravision.egg-info/SOURCES.txt
src/cameravision.egg-info/dependency_links.txt
src/cameravision.egg-info/requires.txt
src/cameravision.egg-info/top_level.txt