Metadata-Version: 2.4
Name: cameravision
Version: 0.3.0
Summary: Manipulate camera calibration parameters and warp images for computer vision tasks.
Author-email: István Sárándi <istvan.sarandi@uni-tuebingen.de>
License-Expression: MIT
Project-URL: Homepage, https://github.com/isarandi/cameravision
Project-URL: Repository, https://github.com/isarandi/cameravision
Project-URL: Issues, https://github.com/isarandi/cameravision/issues
Project-URL: Author, https://istvansarandi.com
Classifier: Development Status :: 4 - Beta
Classifier: Intended Audience :: Developers
Classifier: Intended Audience :: Science/Research
Classifier: Topic :: Scientific/Engineering :: Information Analysis
Classifier: Topic :: Software Development :: Libraries
Classifier: Programming Language :: Python
Classifier: Programming Language :: Python :: 3
Classifier: Operating System :: POSIX :: Linux
Requires-Python: >=3.9
License-File: LICENSE
Requires-Dist: opencv-python
Requires-Dist: numpy
Requires-Dist: scipy
Requires-Dist: numba
Requires-Dist: shapely
Requires-Dist: msgpack-numpy
Requires-Dist: boxlib
Dynamic: license-file
